<?xml version = '1.0' encoding = 'UTF-8'?>
<TableProxyOraclev12c class="oracle.dbtools.crest.model.design.storage.oracle.v12c.TableProxyOraclev12c" name="Administratori" directorySegmentName="seg_0" id="884D3190-3128-DBE5-61F0-9103D1E13457">
<createdBy>cosmi</createdBy>
<createdTime>2020-12-01 14:50:39 UTC</createdTime>
<ownerDesignName>Meniu Restaurant BD-P</ownerDesignName>
<logging>YES</logging>
<partitionedRowMovement>DISABLE</partitionedRowMovement>
<temporaryChanged>false</temporaryChanged>
<accessDriverType>oracle_loader</accessDriverType>
<rejectLimit></rejectLimit>
<columnProxies itemClass="oracle.dbtools.crest.model.design.storage.oracle.v12c.ColumnProxyOraclev12c">
<ColumnProxy name="id_administrator" id="194F45EC-6EC8-E97E-297B-EB3F24B656C1">
<createdBy>cosmi</createdBy>
<createdTime>2020-12-01 14:50:39 UTC</createdTime>
<ownerDesignName>Meniu Restaurant BD-P</ownerDesignName>
</ColumnProxy>
<ColumnProxy name="parola_cont" id="4A28B06C-9DFD-3181-F3AD-75DB0B401A64">
<createdBy>cosmi</createdBy>
<createdTime>2020-12-01 14:50:39 UTC</createdTime>
<ownerDesignName>Meniu Restaurant BD-P</ownerDesignName>
</ColumnProxy>
<ColumnProxy name="nume_prenume_cont" id="D3CDEBBF-BC32-4611-066C-49A7ABC69862">
<createdBy>cosmi</createdBy>
<createdTime>2020-12-01 14:50:39 UTC</createdTime>
<ownerDesignName>Meniu Restaurant BD-P</ownerDesignName>
</ColumnProxy>
</columnProxies>
<primaryKeys>
<PrimaryKey class="oracle.dbtools.crest.model.design.storage.oracle.v10g.PKProxyOraclev10g" name="Administratori_PK" id="206969A5-AB09-6A18-0DAA-552712395900">
<createdBy>cosmi</createdBy>
<createdTime>2020-12-01 14:50:39 UTC</createdTime>
<ownerDesignName>Meniu Restaurant BD-P</ownerDesignName>
<indexSort>SORTED</indexSort>
</PrimaryKey>
</primaryKeys>
</TableProxyOraclev12c>
